{
  "openapi": "3.0.0",
  "info": {
    "title": "ERP RRI - API Documentation",
    "version": "1.0.0",
    "description": "REST API for ERP RRI system. Manages master data including barang, supplier, customer, COA, kontrak, jabatan, karyawan, and more. All endpoints require Bearer JWT authentication obtained from /login."
  },
  "servers": [
    {
      "url": "http://localhost:3000/api",
      "description": "Local development server"
    }
  ],
  "components": {
    "securitySchemes": {
      "BearerAuth": {
        "type": "http",
        "scheme": "bearer",
        "bearerFormat": "JWT"
      }
    },
    "schemas": {},
    "responses": {
      "400": {
        "description": "Bad Request",
        "content": {
          "application/json": {
            "schema": {
              "type": "object",
              "properties": {
                "error": {
                  "type": "string",
                  "example": "Invalid request parameters"
                },
                "code": {
                  "type": "string",
                  "example": "400"
                }
              }
            }
          }
        }
      },
      "401": {
        "description": "Unauthorized",
        "content": {
          "application/json": {
            "schema": {
              "type": "object",
              "properties": {
                "error": {
                  "type": "string",
                  "example": "Authentication required"
                },
                "code": {
                  "type": "string",
                  "example": "401"
                }
              }
            }
          }
        }
      },
      "403": {
        "description": "Forbidden",
        "content": {
          "application/json": {
            "schema": {
              "type": "object",
              "properties": {
                "error": {
                  "type": "string",
                  "example": "Access denied"
                },
                "code": {
                  "type": "string",
                  "example": "403"
                }
              }
            }
          }
        }
      },
      "404": {
        "description": "Not Found",
        "content": {
          "application/json": {
            "schema": {
              "type": "object",
              "properties": {
                "error": {
                  "type": "string",
                  "example": "Resource not found"
                },
                "code": {
                  "type": "string",
                  "example": "404"
                }
              }
            }
          }
        }
      },
      "409": {
        "description": "Conflict",
        "content": {
          "application/json": {
            "schema": {
              "type": "object",
              "properties": {
                "error": {
                  "type": "string",
                  "example": "Resource already exists"
                },
                "code": {
                  "type": "string",
                  "example": "409"
                }
              }
            }
          }
        }
      },
      "500": {
        "description": "Internal Server Error",
        "content": {
          "application/json": {
            "schema": {
              "type": "object",
              "properties": {
                "error": {
                  "type": "string",
                  "example": "An unexpected error occurred"
                },
                "code": {
                  "type": "string",
                  "example": "500"
                }
              }
            }
          }
        }
      }
    }
  },
  "paths": {
    "/v1/master/barang": {
      "get": {
        "operationId": "get-v1-master-barang",
        "summary": "",
        "description": "",
        "tags": [
          "V1"
        ],
        "parameters": [],
        "responses": {
          "200": {
            "description": "Successful response",
            "content": {
              "application/json": {
                "schema": {
                  "type": "object"
                }
              }
            }
          },
          "400": {
            "$ref": "#/components/responses/400"
          },
          "500": {
            "$ref": "#/components/responses/500"
          }
        }
      },
      "post": {
        "operationId": "post-v1-master-barang",
        "summary": "",
        "description": "",
        "tags": [
          "V1"
        ],
        "parameters": [],
        "responses": {
          "201": {
            "description": "Successful response",
            "content": {
              "application/json": {
                "schema": {
                  "type": "object",
                  "properties": {
                    "data": {
                      "type": "object"
                    }
                  },
                  "required": [
                    "data"
                  ]
                }
              }
            }
          },
          "400": {
            "$ref": "#/components/responses/400"
          },
          "500": {
            "$ref": "#/components/responses/500"
          }
        }
      }
    },
    "/v1/master/coa": {
      "get": {
        "operationId": "get-v1-master-coa",
        "summary": "",
        "description": "",
        "tags": [
          "V1"
        ],
        "parameters": [],
        "responses": {
          "200": {
            "description": "Successful response",
            "content": {
              "application/json": {
                "schema": {
                  "type": "object"
                }
              }
            }
          },
          "400": {
            "$ref": "#/components/responses/400"
          },
          "500": {
            "$ref": "#/components/responses/500"
          }
        }
      },
      "post": {
        "operationId": "post-v1-master-coa",
        "summary": "",
        "description": "",
        "tags": [
          "V1"
        ],
        "parameters": [],
        "responses": {
          "201": {
            "description": "Successful response",
            "content": {
              "application/json": {
                "schema": {
                  "type": "object",
                  "properties": {
                    "data": {
                      "type": "object"
                    }
                  },
                  "required": [
                    "data"
                  ]
                }
              }
            }
          },
          "400": {
            "$ref": "#/components/responses/400"
          },
          "500": {
            "$ref": "#/components/responses/500"
          }
        }
      }
    },
    "/v1/master/customer": {
      "get": {
        "operationId": "get-v1-master-customer",
        "summary": "",
        "description": "",
        "tags": [
          "V1"
        ],
        "parameters": [],
        "responses": {
          "200": {
            "description": "Successful response",
            "content": {
              "application/json": {
                "schema": {
                  "type": "object"
                }
              }
            }
          },
          "400": {
            "$ref": "#/components/responses/400"
          },
          "500": {
            "$ref": "#/components/responses/500"
          }
        }
      },
      "post": {
        "operationId": "post-v1-master-customer",
        "summary": "",
        "description": "",
        "tags": [
          "V1"
        ],
        "parameters": [],
        "responses": {
          "201": {
            "description": "Successful response",
            "content": {
              "application/json": {
                "schema": {
                  "type": "object",
                  "properties": {
                    "data": {
                      "type": "object"
                    }
                  },
                  "required": [
                    "data"
                  ]
                }
              }
            }
          },
          "400": {
            "$ref": "#/components/responses/400"
          },
          "500": {
            "$ref": "#/components/responses/500"
          }
        }
      }
    },
    "/v1/master/jabatan": {
      "get": {
        "operationId": "get-v1-master-jabatan",
        "summary": "",
        "description": "",
        "tags": [
          "V1"
        ],
        "parameters": [],
        "responses": {
          "200": {
            "description": "Successful response",
            "content": {
              "application/json": {
                "schema": {
                  "type": "object"
                }
              }
            }
          },
          "400": {
            "$ref": "#/components/responses/400"
          },
          "500": {
            "$ref": "#/components/responses/500"
          }
        }
      },
      "post": {
        "operationId": "post-v1-master-jabatan",
        "summary": "",
        "description": "",
        "tags": [
          "V1"
        ],
        "parameters": [],
        "responses": {
          "201": {
            "description": "Successful response",
            "content": {
              "application/json": {
                "schema": {
                  "type": "object",
                  "properties": {
                    "data": {
                      "type": "object"
                    }
                  },
                  "required": [
                    "data"
                  ]
                }
              }
            }
          },
          "400": {
            "$ref": "#/components/responses/400"
          },
          "500": {
            "$ref": "#/components/responses/500"
          }
        }
      }
    },
    "/v1/master/karyawan": {
      "get": {
        "operationId": "get-v1-master-karyawan",
        "summary": "",
        "description": "",
        "tags": [
          "V1"
        ],
        "parameters": [],
        "responses": {
          "200": {
            "description": "Successful response",
            "content": {
              "application/json": {
                "schema": {
                  "type": "object"
                }
              }
            }
          },
          "400": {
            "$ref": "#/components/responses/400"
          },
          "500": {
            "$ref": "#/components/responses/500"
          }
        }
      },
      "post": {
        "operationId": "post-v1-master-karyawan",
        "summary": "",
        "description": "",
        "tags": [
          "V1"
        ],
        "parameters": [],
        "responses": {
          "201": {
            "description": "Successful response",
            "content": {
              "application/json": {
                "schema": {
                  "type": "object",
                  "properties": {
                    "data": {
                      "type": "object"
                    }
                  },
                  "required": [
                    "data"
                  ]
                }
              }
            }
          },
          "400": {
            "$ref": "#/components/responses/400"
          },
          "500": {
            "$ref": "#/components/responses/500"
          }
        }
      }
    },
    "/v1/master/kategori-barang": {
      "get": {
        "operationId": "get-v1-master-kategori-barang",
        "summary": "",
        "description": "",
        "tags": [
          "V1"
        ],
        "parameters": [],
        "responses": {
          "200": {
            "description": "Successful response",
            "content": {
              "application/json": {
                "schema": {
                  "type": "object"
                }
              }
            }
          },
          "400": {
            "$ref": "#/components/responses/400"
          },
          "500": {
            "$ref": "#/components/responses/500"
          }
        }
      },
      "post": {
        "operationId": "post-v1-master-kategori-barang",
        "summary": "",
        "description": "",
        "tags": [
          "V1"
        ],
        "parameters": [],
        "responses": {
          "201": {
            "description": "Successful response",
            "content": {
              "application/json": {
                "schema": {
                  "type": "object",
                  "properties": {
                    "data": {
                      "type": "object"
                    }
                  },
                  "required": [
                    "data"
                  ]
                }
              }
            }
          },
          "400": {
            "$ref": "#/components/responses/400"
          },
          "500": {
            "$ref": "#/components/responses/500"
          }
        }
      }
    },
    "/v1/master/kontrak": {
      "get": {
        "operationId": "get-v1-master-kontrak",
        "summary": "",
        "description": "",
        "tags": [
          "V1"
        ],
        "parameters": [],
        "responses": {
          "200": {
            "description": "Successful response",
            "content": {
              "application/json": {
                "schema": {
                  "type": "object"
                }
              }
            }
          },
          "400": {
            "$ref": "#/components/responses/400"
          },
          "500": {
            "$ref": "#/components/responses/500"
          }
        }
      },
      "post": {
        "operationId": "post-v1-master-kontrak",
        "summary": "",
        "description": "",
        "tags": [
          "V1"
        ],
        "parameters": [],
        "responses": {
          "201": {
            "description": "Successful response",
            "content": {
              "application/json": {
                "schema": {
                  "type": "object",
                  "properties": {
                    "data": {
                      "type": "object"
                    }
                  },
                  "required": [
                    "data"
                  ]
                }
              }
            }
          },
          "400": {
            "$ref": "#/components/responses/400"
          },
          "500": {
            "$ref": "#/components/responses/500"
          }
        }
      }
    },
    "/v1/master/pic-customer": {
      "get": {
        "operationId": "get-v1-master-pic-customer",
        "summary": "",
        "description": "",
        "tags": [
          "V1"
        ],
        "parameters": [],
        "responses": {
          "200": {
            "description": "Successful response",
            "content": {
              "application/json": {
                "schema": {
                  "type": "object"
                }
              }
            }
          },
          "400": {
            "$ref": "#/components/responses/400"
          },
          "500": {
            "$ref": "#/components/responses/500"
          }
        }
      },
      "post": {
        "operationId": "post-v1-master-pic-customer",
        "summary": "",
        "description": "",
        "tags": [
          "V1"
        ],
        "parameters": [],
        "responses": {
          "201": {
            "description": "Successful response",
            "content": {
              "application/json": {
                "schema": {
                  "type": "object",
                  "properties": {
                    "data": {
                      "type": "object"
                    }
                  },
                  "required": [
                    "data"
                  ]
                }
              }
            }
          },
          "400": {
            "$ref": "#/components/responses/400"
          },
          "500": {
            "$ref": "#/components/responses/500"
          }
        }
      }
    },
    "/v1/master/supplier": {
      "get": {
        "operationId": "get-v1-master-supplier",
        "summary": "",
        "description": "",
        "tags": [
          "V1"
        ],
        "parameters": [],
        "responses": {
          "200": {
            "description": "Successful response",
            "content": {
              "application/json": {
                "schema": {
                  "type": "object"
                }
              }
            }
          },
          "400": {
            "$ref": "#/components/responses/400"
          },
          "500": {
            "$ref": "#/components/responses/500"
          }
        }
      },
      "post": {
        "operationId": "post-v1-master-supplier",
        "summary": "",
        "description": "",
        "tags": [
          "V1"
        ],
        "parameters": [],
        "responses": {
          "201": {
            "description": "Successful response",
            "content": {
              "application/json": {
                "schema": {
                  "type": "object",
                  "properties": {
                    "data": {
                      "type": "object"
                    }
                  },
                  "required": [
                    "data"
                  ]
                }
              }
            }
          },
          "400": {
            "$ref": "#/components/responses/400"
          },
          "500": {
            "$ref": "#/components/responses/500"
          }
        }
      }
    },
    "/v1/master/barang/{id}": {
      "get": {
        "operationId": "get-v1-master-barang-{id}",
        "summary": "",
        "description": "",
        "tags": [
          "V1"
        ],
        "parameters": [
          {
            "name": "id",
            "in": "path",
            "required": true,
            "schema": {
              "type": "number"
            },
            "example": 123,
            "description": "Path parameter: id"
          }
        ],
        "responses": {
          "200": {
            "description": "Successful response",
            "content": {
              "application/json": {
                "schema": {
                  "type": "object"
                }
              }
            }
          },
          "400": {
            "$ref": "#/components/responses/400"
          },
          "500": {
            "$ref": "#/components/responses/500"
          }
        }
      },
      "put": {
        "operationId": "put-v1-master-barang-{id}",
        "summary": "",
        "description": "",
        "tags": [
          "V1"
        ],
        "parameters": [
          {
            "name": "id",
            "in": "path",
            "required": true,
            "schema": {
              "type": "number"
            },
            "example": 123,
            "description": "Path parameter: id"
          }
        ],
        "responses": {
          "200": {
            "description": "Successful response",
            "content": {
              "application/json": {
                "schema": {
                  "type": "object"
                }
              }
            }
          },
          "400": {
            "$ref": "#/components/responses/400"
          },
          "500": {
            "$ref": "#/components/responses/500"
          }
        }
      },
      "delete": {
        "operationId": "delete-v1-master-barang-{id}",
        "summary": "",
        "description": "",
        "tags": [
          "V1"
        ],
        "parameters": [
          {
            "name": "id",
            "in": "path",
            "required": true,
            "schema": {
              "type": "number"
            },
            "example": 123,
            "description": "Path parameter: id"
          }
        ],
        "responses": {
          "200": {
            "description": "Successful response",
            "content": {
              "application/json": {
                "schema": {
                  "type": "object"
                }
              }
            }
          },
          "400": {
            "$ref": "#/components/responses/400"
          },
          "500": {
            "$ref": "#/components/responses/500"
          }
        }
      }
    },
    "/v1/master/coa/{id}": {
      "get": {
        "operationId": "get-v1-master-coa-{id}",
        "summary": "",
        "description": "",
        "tags": [
          "V1"
        ],
        "parameters": [
          {
            "name": "id",
            "in": "path",
            "required": true,
            "schema": {
              "type": "number"
            },
            "example": 123,
            "description": "Path parameter: id"
          }
        ],
        "responses": {
          "200": {
            "description": "Successful response",
            "content": {
              "application/json": {
                "schema": {
                  "type": "object"
                }
              }
            }
          },
          "400": {
            "$ref": "#/components/responses/400"
          },
          "500": {
            "$ref": "#/components/responses/500"
          }
        }
      },
      "put": {
        "operationId": "put-v1-master-coa-{id}",
        "summary": "",
        "description": "",
        "tags": [
          "V1"
        ],
        "parameters": [
          {
            "name": "id",
            "in": "path",
            "required": true,
            "schema": {
              "type": "number"
            },
            "example": 123,
            "description": "Path parameter: id"
          }
        ],
        "responses": {
          "200": {
            "description": "Successful response",
            "content": {
              "application/json": {
                "schema": {
                  "type": "object"
                }
              }
            }
          },
          "400": {
            "$ref": "#/components/responses/400"
          },
          "500": {
            "$ref": "#/components/responses/500"
          }
        }
      },
      "delete": {
        "operationId": "delete-v1-master-coa-{id}",
        "summary": "",
        "description": "",
        "tags": [
          "V1"
        ],
        "parameters": [
          {
            "name": "id",
            "in": "path",
            "required": true,
            "schema": {
              "type": "number"
            },
            "example": 123,
            "description": "Path parameter: id"
          }
        ],
        "responses": {
          "200": {
            "description": "Successful response",
            "content": {
              "application/json": {
                "schema": {
                  "type": "object"
                }
              }
            }
          },
          "400": {
            "$ref": "#/components/responses/400"
          },
          "500": {
            "$ref": "#/components/responses/500"
          }
        }
      }
    },
    "/v1/master/customer/{id}": {
      "get": {
        "operationId": "get-v1-master-customer-{id}",
        "summary": "",
        "description": "",
        "tags": [
          "V1"
        ],
        "parameters": [
          {
            "name": "id",
            "in": "path",
            "required": true,
            "schema": {
              "type": "number"
            },
            "example": 123,
            "description": "Path parameter: id"
          }
        ],
        "responses": {
          "200": {
            "description": "Successful response",
            "content": {
              "application/json": {
                "schema": {
                  "type": "object"
                }
              }
            }
          },
          "400": {
            "$ref": "#/components/responses/400"
          },
          "500": {
            "$ref": "#/components/responses/500"
          }
        }
      },
      "put": {
        "operationId": "put-v1-master-customer-{id}",
        "summary": "",
        "description": "",
        "tags": [
          "V1"
        ],
        "parameters": [
          {
            "name": "id",
            "in": "path",
            "required": true,
            "schema": {
              "type": "number"
            },
            "example": 123,
            "description": "Path parameter: id"
          }
        ],
        "responses": {
          "200": {
            "description": "Successful response",
            "content": {
              "application/json": {
                "schema": {
                  "type": "object"
                }
              }
            }
          },
          "400": {
            "$ref": "#/components/responses/400"
          },
          "500": {
            "$ref": "#/components/responses/500"
          }
        }
      },
      "delete": {
        "operationId": "delete-v1-master-customer-{id}",
        "summary": "",
        "description": "",
        "tags": [
          "V1"
        ],
        "parameters": [
          {
            "name": "id",
            "in": "path",
            "required": true,
            "schema": {
              "type": "number"
            },
            "example": 123,
            "description": "Path parameter: id"
          }
        ],
        "responses": {
          "200": {
            "description": "Successful response",
            "content": {
              "application/json": {
                "schema": {
                  "type": "object"
                }
              }
            }
          },
          "400": {
            "$ref": "#/components/responses/400"
          },
          "500": {
            "$ref": "#/components/responses/500"
          }
        }
      }
    },
    "/v1/master/jabatan/{id}": {
      "get": {
        "operationId": "get-v1-master-jabatan-{id}",
        "summary": "",
        "description": "",
        "tags": [
          "V1"
        ],
        "parameters": [
          {
            "name": "id",
            "in": "path",
            "required": true,
            "schema": {
              "type": "number"
            },
            "example": 123,
            "description": "Path parameter: id"
          }
        ],
        "responses": {
          "200": {
            "description": "Successful response",
            "content": {
              "application/json": {
                "schema": {
                  "type": "object"
                }
              }
            }
          },
          "400": {
            "$ref": "#/components/responses/400"
          },
          "500": {
            "$ref": "#/components/responses/500"
          }
        }
      },
      "put": {
        "operationId": "put-v1-master-jabatan-{id}",
        "summary": "",
        "description": "",
        "tags": [
          "V1"
        ],
        "parameters": [
          {
            "name": "id",
            "in": "path",
            "required": true,
            "schema": {
              "type": "number"
            },
            "example": 123,
            "description": "Path parameter: id"
          }
        ],
        "responses": {
          "200": {
            "description": "Successful response",
            "content": {
              "application/json": {
                "schema": {
                  "type": "object"
                }
              }
            }
          },
          "400": {
            "$ref": "#/components/responses/400"
          },
          "500": {
            "$ref": "#/components/responses/500"
          }
        }
      },
      "delete": {
        "operationId": "delete-v1-master-jabatan-{id}",
        "summary": "",
        "description": "",
        "tags": [
          "V1"
        ],
        "parameters": [
          {
            "name": "id",
            "in": "path",
            "required": true,
            "schema": {
              "type": "number"
            },
            "example": 123,
            "description": "Path parameter: id"
          }
        ],
        "responses": {
          "200": {
            "description": "Successful response",
            "content": {
              "application/json": {
                "schema": {
                  "type": "object"
                }
              }
            }
          },
          "400": {
            "$ref": "#/components/responses/400"
          },
          "500": {
            "$ref": "#/components/responses/500"
          }
        }
      }
    },
    "/v1/master/karyawan/{id}": {
      "get": {
        "operationId": "get-v1-master-karyawan-{id}",
        "summary": "",
        "description": "",
        "tags": [
          "V1"
        ],
        "parameters": [
          {
            "name": "id",
            "in": "path",
            "required": true,
            "schema": {
              "type": "number"
            },
            "example": 123,
            "description": "Path parameter: id"
          }
        ],
        "responses": {
          "200": {
            "description": "Successful response",
            "content": {
              "application/json": {
                "schema": {
                  "type": "object"
                }
              }
            }
          },
          "400": {
            "$ref": "#/components/responses/400"
          },
          "500": {
            "$ref": "#/components/responses/500"
          }
        }
      },
      "put": {
        "operationId": "put-v1-master-karyawan-{id}",
        "summary": "",
        "description": "",
        "tags": [
          "V1"
        ],
        "parameters": [
          {
            "name": "id",
            "in": "path",
            "required": true,
            "schema": {
              "type": "number"
            },
            "example": 123,
            "description": "Path parameter: id"
          }
        ],
        "responses": {
          "200": {
            "description": "Successful response",
            "content": {
              "application/json": {
                "schema": {
                  "type": "object"
                }
              }
            }
          },
          "400": {
            "$ref": "#/components/responses/400"
          },
          "500": {
            "$ref": "#/components/responses/500"
          }
        }
      },
      "delete": {
        "operationId": "delete-v1-master-karyawan-{id}",
        "summary": "",
        "description": "",
        "tags": [
          "V1"
        ],
        "parameters": [
          {
            "name": "id",
            "in": "path",
            "required": true,
            "schema": {
              "type": "number"
            },
            "example": 123,
            "description": "Path parameter: id"
          }
        ],
        "responses": {
          "200": {
            "description": "Successful response",
            "content": {
              "application/json": {
                "schema": {
                  "type": "object"
                }
              }
            }
          },
          "400": {
            "$ref": "#/components/responses/400"
          },
          "500": {
            "$ref": "#/components/responses/500"
          }
        }
      }
    },
    "/v1/master/kategori-barang/{id}": {
      "get": {
        "operationId": "get-v1-master-kategori-barang-{id}",
        "summary": "",
        "description": "",
        "tags": [
          "V1"
        ],
        "parameters": [
          {
            "name": "id",
            "in": "path",
            "required": true,
            "schema": {
              "type": "number"
            },
            "example": 123,
            "description": "Path parameter: id"
          }
        ],
        "responses": {
          "200": {
            "description": "Successful response",
            "content": {
              "application/json": {
                "schema": {
                  "type": "object"
                }
              }
            }
          },
          "400": {
            "$ref": "#/components/responses/400"
          },
          "500": {
            "$ref": "#/components/responses/500"
          }
        }
      },
      "put": {
        "operationId": "put-v1-master-kategori-barang-{id}",
        "summary": "",
        "description": "",
        "tags": [
          "V1"
        ],
        "parameters": [
          {
            "name": "id",
            "in": "path",
            "required": true,
            "schema": {
              "type": "number"
            },
            "example": 123,
            "description": "Path parameter: id"
          }
        ],
        "responses": {
          "200": {
            "description": "Successful response",
            "content": {
              "application/json": {
                "schema": {
                  "type": "object"
                }
              }
            }
          },
          "400": {
            "$ref": "#/components/responses/400"
          },
          "500": {
            "$ref": "#/components/responses/500"
          }
        }
      },
      "delete": {
        "operationId": "delete-v1-master-kategori-barang-{id}",
        "summary": "",
        "description": "",
        "tags": [
          "V1"
        ],
        "parameters": [
          {
            "name": "id",
            "in": "path",
            "required": true,
            "schema": {
              "type": "number"
            },
            "example": 123,
            "description": "Path parameter: id"
          }
        ],
        "responses": {
          "200": {
            "description": "Successful response",
            "content": {
              "application/json": {
                "schema": {
                  "type": "object"
                }
              }
            }
          },
          "400": {
            "$ref": "#/components/responses/400"
          },
          "500": {
            "$ref": "#/components/responses/500"
          }
        }
      }
    },
    "/v1/master/kontrak/{id}": {
      "get": {
        "operationId": "get-v1-master-kontrak-{id}",
        "summary": "",
        "description": "",
        "tags": [
          "V1"
        ],
        "parameters": [
          {
            "name": "id",
            "in": "path",
            "required": true,
            "schema": {
              "type": "number"
            },
            "example": 123,
            "description": "Path parameter: id"
          }
        ],
        "responses": {
          "200": {
            "description": "Successful response",
            "content": {
              "application/json": {
                "schema": {
                  "type": "object"
                }
              }
            }
          },
          "400": {
            "$ref": "#/components/responses/400"
          },
          "500": {
            "$ref": "#/components/responses/500"
          }
        }
      },
      "put": {
        "operationId": "put-v1-master-kontrak-{id}",
        "summary": "",
        "description": "",
        "tags": [
          "V1"
        ],
        "parameters": [
          {
            "name": "id",
            "in": "path",
            "required": true,
            "schema": {
              "type": "number"
            },
            "example": 123,
            "description": "Path parameter: id"
          }
        ],
        "responses": {
          "200": {
            "description": "Successful response",
            "content": {
              "application/json": {
                "schema": {
                  "type": "object"
                }
              }
            }
          },
          "400": {
            "$ref": "#/components/responses/400"
          },
          "500": {
            "$ref": "#/components/responses/500"
          }
        }
      },
      "delete": {
        "operationId": "delete-v1-master-kontrak-{id}",
        "summary": "",
        "description": "",
        "tags": [
          "V1"
        ],
        "parameters": [
          {
            "name": "id",
            "in": "path",
            "required": true,
            "schema": {
              "type": "number"
            },
            "example": 123,
            "description": "Path parameter: id"
          }
        ],
        "responses": {
          "200": {
            "description": "Successful response",
            "content": {
              "application/json": {
                "schema": {
                  "type": "object"
                }
              }
            }
          },
          "400": {
            "$ref": "#/components/responses/400"
          },
          "500": {
            "$ref": "#/components/responses/500"
          }
        }
      }
    },
    "/v1/master/pic-customer/{id}": {
      "get": {
        "operationId": "get-v1-master-pic-customer-{id}",
        "summary": "",
        "description": "",
        "tags": [
          "V1"
        ],
        "parameters": [
          {
            "name": "id",
            "in": "path",
            "required": true,
            "schema": {
              "type": "number"
            },
            "example": 123,
            "description": "Path parameter: id"
          }
        ],
        "responses": {
          "200": {
            "description": "Successful response",
            "content": {
              "application/json": {
                "schema": {
                  "type": "object"
                }
              }
            }
          },
          "400": {
            "$ref": "#/components/responses/400"
          },
          "500": {
            "$ref": "#/components/responses/500"
          }
        }
      },
      "put": {
        "operationId": "put-v1-master-pic-customer-{id}",
        "summary": "",
        "description": "",
        "tags": [
          "V1"
        ],
        "parameters": [
          {
            "name": "id",
            "in": "path",
            "required": true,
            "schema": {
              "type": "number"
            },
            "example": 123,
            "description": "Path parameter: id"
          }
        ],
        "responses": {
          "200": {
            "description": "Successful response",
            "content": {
              "application/json": {
                "schema": {
                  "type": "object"
                }
              }
            }
          },
          "400": {
            "$ref": "#/components/responses/400"
          },
          "500": {
            "$ref": "#/components/responses/500"
          }
        }
      },
      "delete": {
        "operationId": "delete-v1-master-pic-customer-{id}",
        "summary": "",
        "description": "",
        "tags": [
          "V1"
        ],
        "parameters": [
          {
            "name": "id",
            "in": "path",
            "required": true,
            "schema": {
              "type": "number"
            },
            "example": 123,
            "description": "Path parameter: id"
          }
        ],
        "responses": {
          "200": {
            "description": "Successful response",
            "content": {
              "application/json": {
                "schema": {
                  "type": "object"
                }
              }
            }
          },
          "400": {
            "$ref": "#/components/responses/400"
          },
          "500": {
            "$ref": "#/components/responses/500"
          }
        }
      }
    },
    "/v1/master/supplier/{id}": {
      "get": {
        "operationId": "get-v1-master-supplier-{id}",
        "summary": "",
        "description": "",
        "tags": [
          "V1"
        ],
        "parameters": [
          {
            "name": "id",
            "in": "path",
            "required": true,
            "schema": {
              "type": "number"
            },
            "example": 123,
            "description": "Path parameter: id"
          }
        ],
        "responses": {
          "200": {
            "description": "Successful response",
            "content": {
              "application/json": {
                "schema": {
                  "type": "object"
                }
              }
            }
          },
          "400": {
            "$ref": "#/components/responses/400"
          },
          "500": {
            "$ref": "#/components/responses/500"
          }
        }
      },
      "put": {
        "operationId": "put-v1-master-supplier-{id}",
        "summary": "",
        "description": "",
        "tags": [
          "V1"
        ],
        "parameters": [
          {
            "name": "id",
            "in": "path",
            "required": true,
            "schema": {
              "type": "number"
            },
            "example": 123,
            "description": "Path parameter: id"
          }
        ],
        "responses": {
          "200": {
            "description": "Successful response",
            "content": {
              "application/json": {
                "schema": {
                  "type": "object"
                }
              }
            }
          },
          "400": {
            "$ref": "#/components/responses/400"
          },
          "500": {
            "$ref": "#/components/responses/500"
          }
        }
      },
      "delete": {
        "operationId": "delete-v1-master-supplier-{id}",
        "summary": "",
        "description": "",
        "tags": [
          "V1"
        ],
        "parameters": [
          {
            "name": "id",
            "in": "path",
            "required": true,
            "schema": {
              "type": "number"
            },
            "example": 123,
            "description": "Path parameter: id"
          }
        ],
        "responses": {
          "200": {
            "description": "Successful response",
            "content": {
              "application/json": {
                "schema": {
                  "type": "object"
                }
              }
            }
          },
          "400": {
            "$ref": "#/components/responses/400"
          },
          "500": {
            "$ref": "#/components/responses/500"
          }
        }
      }
    }
  },
  "tags": [
    {
      "name": "V1"
    }
  ]
}
